wrilytextaligner/README.MD
wrilytextaligner/__init__.py
wrilytextaligner/requirements.txt
wrilytextaligner/thirdparty.json
wrilytextaligner-0.10.dist-info/LICENSE.rst
wrilytextaligner-0.10.dist-info/METADATA
wrilytextaligner-0.10.dist-info/WHEEL
wrilytextaligner-0.10.dist-info/top_level.txt
wrilytextaligner-0.10.dist-info/RECORD
