Metadata-Version: 2.1
Name: wrilytextaligner
Version: 0.10
Summary: Aligns text lines and characters within an image
Home-page: https://github.com/hansalemaos/wrilytextaligner
Author: Johannes Fischer
Author-email: aulasparticularesdealemaosp@gmail.com
License: MIT
Keywords: text,align
Classifier: Development Status :: 4 - Beta
Classifier: Programming Language :: Python :: 3 :: Only
Classifier: Programming Language :: Python :: 3.10
Classifier: Topic :: Software Development :: Libraries :: Python Modules
Classifier: Topic :: Utilities
License-File: LICENSE.rst
Requires-Dist: a-cv2-easy-resize
Requires-Dist: a-cv-imwrite-imread-plus
Requires-Dist: intersection-grouper
Requires-Dist: numpy
Requires-Dist: opencv-python
